eldar_math_duel/__init__.py
eldar_math_duel/game.py
eldar_math_duel-1.0.0.dist-info/licenses/LICENSE
eldar_math_duel-1.0.0.dist-info/METADATA
eldar_math_duel-1.0.0.dist-info/WHEEL
eldar_math_duel-1.0.0.dist-info/entry_points.txt
eldar_math_duel-1.0.0.dist-info/top_level.txt
eldar_math_duel-1.0.0.dist-info/RECORD
