Metadata-Version: 2.4
Name: eldar-math-duel
Version: 1.0.0
Summary: Two-player Math Duel terminal game
Author: Eldar
Requires-Python: >=3.8
License-File: LICENSE
Dynamic: author
Dynamic: description
Dynamic: description-content-type
Dynamic: license-file
Dynamic: requires-python
Dynamic: summary
